catholic/__init__.py
catholic/catholic.py
catholic/commands/__init__.py
catholic/commands/choice.py
catholic/core/__init__.py
catholic/core/canon/__init__.py
catholic/core/canon/api.py
catholic/core/canon/services.py
catholic/core/catechism/__init__.py
catholic/core/catechism/api.py
catholic/core/catechism/services.py
catholic/core/missal/__init__.py
catholic/core/missal/api.py
catholic/core/missal/services.py
catholic/core/utils/__init__.py
catholic/core/utils/console.py
catholic/core/utils/docs.py
catholic/core/utils/files.py
catholic/core/utils/interact.py
catholic/core/utils/query.py
catholic/core/utils/strings.py
catholic/index/__init__.py
catholic/index/genesis.py
catholic/index/canon_index/MAIN_WRITELOCK
catholic/index/canon_index/MAIN_jcfftbwmodlertj6.seg
catholic/index/canon_index/_MAIN_1.toc
catholic/index/catechism_index/MAIN_WRITELOCK
catholic/index/catechism_index/MAIN_x9ce2efhbz9dvnt0.seg
catholic/index/catechism_index/_MAIN_1.toc
catholic/index/missal_index/MAIN_WRITELOCK
catholic/index/missal_index/MAIN_jg57nqsiitr2bdya.seg
catholic/index/missal_index/_MAIN_1.toc
catholic/pickles/__init__.py
catholic/pickles/canon.pickle
catholic/pickles/catechism.pickle
catholic/pickles/girm.pickle
catholic/version/__init__.py
catholic_cli-1.0.0.data/data/catholic/index/MAIN_WRITELOCK
catholic_cli-1.0.0.data/data/catholic/index/MAIN_jcfftbwmodlertj6.seg
catholic_cli-1.0.0.data/data/catholic/index/MAIN_jg57nqsiitr2bdya.seg
catholic_cli-1.0.0.data/data/catholic/index/MAIN_x9ce2efhbz9dvnt0.seg
catholic_cli-1.0.0.data/data/catholic/index/_MAIN_1.toc
catholic_cli-1.0.0.data/data/catholic/pickles/canon.pickle
catholic_cli-1.0.0.data/data/catholic/pickles/catechism.pickle
catholic_cli-1.0.0.data/data/catholic/pickles/girm.pickle
catholic_cli-1.0.0.dist-info/LICENSE
catholic_cli-1.0.0.dist-info/METADATA
catholic_cli-1.0.0.dist-info/WHEEL
catholic_cli-1.0.0.dist-info/entry_points.txt
catholic_cli-1.0.0.dist-info/top_level.txt
catholic_cli-1.0.0.dist-info/RECORD
