Metadata-Version: 2.1
Name: catholic-cli
Version: 1.0.0
Summary: A Command Line Utility for Accessing Information Related to The Catholic Church
Home-page: https://github.com/aseemsavio/catholic-cli/blob/master/README.md
Author: Aseem Savio
Author-email: aseemsavio3@gmail.com
License: MIT
Keywords: christianity,catholicism,catholic,christian,religion,cli
Classifier: Programming Language :: Python :: 3
Classifier: License :: OSI Approved :: MIT License
Classifier: Operating System :: OS Independent
License-File: LICENSE
Requires-Dist: typer[all] (>=0.7.0)
Requires-Dist: Click (>=7)
Requires-Dist: rich (>=12)
Requires-Dist: questionary (>=1.10.0)
Requires-Dist: Whoosh (==2.7.4)
